brawndo/__init__.py
brawndo/brawndo.py
brawndo/constants.py
brawndo-1.0.1.dist-info/LICENSE
brawndo-1.0.1.dist-info/METADATA
brawndo-1.0.1.dist-info/WHEEL
brawndo-1.0.1.dist-info/top_level.txt
brawndo-1.0.1.dist-info/RECORD
