Metadata-Version: 2.1
Name: brawndo
Version: 1.0.1
Summary: Makes your terminal text chaotic. It's got what plants crave!
Author-email: Michael Lin <mal9608@nyu.edu>, Seolin Jung <sj3182@nyu.edu>, Marwan AbdElhameed <mwa7459@nyu.edu>, Pavly Halim <poh2005@nyu.edu>
Project-URL: Homepage, https://github.com/software-students-fall2023/3-python-package-exercise-team-not-sure
Project-URL: Repository, https://github.com/software-students-fall2023/3-python-package-exercise-team-not-sure.git
Project-URL: Bug Tracker, https://github.com/software-students-fall2023/3-python-package-exercise-team-not-sure/issues
Classifier: Programming Language :: Python :: 3
Classifier: License :: OSI Approved :: GNU General Public License v3 (GPLv3)
Classifier: Operating System :: OS Independent
Requires-Python: >=3.11
License-File: LICENSE
Requires-Dist: build
Requires-Dist: pytest
Requires-Dist: twine
Requires-Dist: termcolor
Requires-Dist: colorama
Requires-Dist: nltk
